LICENSE
MANIFEST.in
README.rst
requirements.txt
setup.cfg
setup.py
suod/__init__.py
suod/version.py
suod.egg-info/PKG-INFO
suod.egg-info/SOURCES.txt
suod.egg-info/dependency_links.txt
suod.egg-info/requires.txt
suod.egg-info/top_level.txt
suod/models/__init__.py
suod/models/base.py
suod/models/cost_predictor.py
suod/models/jl_projection.py
suod/models/parallel_processes.py
suod/models/saved_models/__init__.py
suod/models/saved_models/summary_prediction.txt
suod/models/saved_models/summary_prediction.xlsx
suod/models/saved_models/summary_train.txt
suod/models/saved_models/summary_train.xlsx
suod/utils/__init__.py
suod/utils/utility.py