Metadata-Version: 2.1
Name: suod
Version: 0.1.3
Summary: A Scalable Framework for Unsupervised Outlier Detection (Anomaly Detection)
Home-page: https://github.com/yzhao062/suod
Author: Yue Zhao
Author-email: yzhao062@gmail.com
License: UNKNOWN
Download-URL: https://github.com/yzhao062/suod/archive/master.zip
Keywords: ensemble learning,anomaly detection,outlier ensembles,data mining,machine learning,python
Platform: UNKNOWN
Classifier: Development Status :: 5 - Production/Stable
Classifier: Intended Audience :: Education
Classifier: Intended Audience :: Financial and Insurance Industry
Classifier: Intended Audience :: Science/Research
Classifier: Intended Audience :: Developers
Classifier: Intended Audience :: Information Technology
Classifier: License :: OSI Approved :: BSD License
Classifier: Programming Language :: Python :: 3.5
Classifier: Programming Language :: Python :: 3.6
Classifier: Programming Language :: Python :: 3.7
License-File: LICENSE
